echod/mock.py
echod/__init__.py
echod/echod.py
echod/utils.py
echod/api.py
echod/callback.py
echod/proxy.py
echod-0.1.0.dist-info/METADATA
echod-0.1.0.dist-info/top_level.txt
echod-0.1.0.dist-info/DESCRIPTION.rst
echod-0.1.0.dist-info/WHEEL
echod-0.1.0.dist-info/entry_points.txt
echod-0.1.0.dist-info/metadata.json
echod-0.1.0.dist-info/RECORD
